[
  {
    "relations": "PARIS - DIJON",
    "annee": "1920",
    "temps_estime_en_minutes": 296.0
  },
  {
    "relations": "PARIS - NICE",
    "annee": "1920",
    "temps_estime_en_minutes": 898.0
  },
  {
    "relations": "PARIS - BORDEAUX",
    "annee": "1928",
    "temps_estime_en_minutes": 580.0
  },
  {
    "relations": "PARIS - LE HAVRE",
    "annee": "1928",
    "temps_estime_en_minutes": 160.0
  },
  {
    "relations": "PARIS - BREST",
    "annee": "1931",
    "temps_estime_en_minutes": 469.0
  },
  {
    "relations": "PARIS - STRASBOURG",
    "annee": "1931",
    "temps_estime_en_minutes": 336.0
  },
  {
    "relations": "PARIS - LE HAVRE",
    "annee": "1932",
    "temps_estime_en_minutes": 144.0
  },
  {
    "relations": "PARIS - LILLE",
    "annee": "1932",
    "temps_estime_en_minutes": 160.0
  },
  {
    "relations": "PARIS - LILLE",
    "annee": "1935",
    "temps_estime_en_minutes": 162.0
  },
  {
    "relations": "PARIS - BORDEAUX",
    "annee": "1936",
    "temps_estime_en_minutes": 344.0
  },
  {
    "relations": "PARIS - BORDEAUX",
    "annee": "1948",
    "temps_estime_en_minutes": 365.0
  },
  {
    "relations": "PARIS - LE HAVRE",
    "annee": "1948",
    "temps_estime_en_minutes": 148.0
  },
  {
    "relations": "PARIS - STRASBOURG",
    "annee": "1950",
    "temps_estime_en_minutes": 315.0
  },
  {
    "relations": "PARIS - MARSEILLE",
    "annee": "1951",
    "temps_estime_en_minutes": 516.0
  },
  {
    "relations": "PARIS - STRASBOURG",
    "annee": "1951",
    "temps_estime_en_minutes": 315.0
  },
  {
    "relations": "PARIS - BREST",
    "annee": "1952",
    "temps_estime_en_minutes": 465.0
  },
  {
    "relations": "PARIS - TOULOUSE",
    "annee": "1952",
    "temps_estime_en_minutes": 515.0
  },
  {
    "relations": "PARIS - BREST",
    "annee": "1953",
    "temps_estime_en_minutes": 471.0
  },
  {
    "relations": "PARIS - MARSEILLE",
    "annee": "1953",
    "temps_estime_en_minutes": 487.0
  },
  {
    "relations": "PARIS - AMIENS",
    "annee": "1954",
    "temps_estime_en_minutes": 74.0
  },
  {
    "relations": "PARIS - BORDEAUX",
    "annee": "1954",
    "temps_estime_en_minutes": 310.0
  },
  {
    "relations": "PARIS - BOULOGNE",
    "annee": "1954",
    "temps_estime_en_minutes": 166.0
  },
  {
    "relations": "PARIS - LYON",
    "annee": "1954",
    "temps_estime_en_minutes": 250.0
  },
  {
    "relations": "PARIS - MARSEILLE",
    "annee": "1954",
    "temps_estime_en_minutes": 483.0
  },
  {
    "relations": "PARIS - STRASBOURG",
    "annee": "1954",
    "temps_estime_en_minutes": 310.0
  },
  {
    "relations": "PARIS - TOULOUSE",
    "annee": "1954",
    "temps_estime_en_minutes": 510.0
  },
  {
    "relations": "PARIS - DIJON",
    "annee": "1955",
    "temps_estime_en_minutes": 152.0
  },
  {
    "relations": "PARIS - DIJON",
    "annee": "1956",
    "temps_estime_en_minutes": 146.0
  },
  {
    "relations": "PARIS - LILLE",
    "annee": "1956",
    "temps_estime_en_minutes": 151.0
  },
  {
    "relations": "PARIS - MARSEILLE",
    "annee": "1956",
    "temps_estime_en_minutes": 472.0
  },
  {
    "relations": "PARIS - LE HAVRE",
    "annee": "1957",
    "temps_estime_en_minutes": 142.0
  },
  {
    "relations": "PARIS - LYON",
    "annee": "1957",
    "temps_estime_en_minutes": 240.0
  },
  {
    "relations": "PARIS - BREST",
    "annee": "1958",
    "temps_estime_en_minutes": 457.0
  },
  {
    "relations": "PARIS - LE HAVRE",
    "annee": "1958",
    "temps_estime_en_minutes": 142.0
  },
  {
    "relations": "PARIS - LIMOGES",
    "annee": "1958",
    "temps_estime_en_minutes": 236.0
  },
  {
    "relations": "PARIS - LYON",
    "annee": "1958",
    "temps_estime_en_minutes": 240.0
  },
  {
    "relations": "PARIS - METZ",
    "annee": "1958",
    "temps_estime_en_minutes": 233.0
  },
  {
    "relations": "PARIS - NARBONNE",
    "annee": "1958",
    "temps_estime_en_minutes": 570.0
  },
  {
    "relations": "PARIS - ST ETIENNE",
    "annee": "1958",
    "temps_estime_en_minutes": 297.0
  },
  {
    "relations": "PARIS - RENNES",
    "annee": "1959",
    "temps_estime_en_minutes": 235.0
  },
  {
    "relations": "PARIS - STRASBOURG",
    "annee": "1959",
    "temps_estime_en_minutes": 311.0
  },
  {
    "relations": "BORDEAUX - MARSEILLE",
    "annee": "1960",
    "temps_estime_en_minutes": 555.0
  },
  {
    "relations": "PARIS - BAYONNE",
    "annee": "1960",
    "temps_estime_en_minutes": 387.0
  },
  {
    "relations": "PARIS - CLERMONT FERRAND",
    "annee": "1960",
    "temps_estime_en_minutes": 240.0
  },
  {
    "relations": "PARIS - LE HAVRE",
    "annee": "1960",
    "temps_estime_en_minutes": 139.0
  },
  {
    "relations": "PARIS - MULHOUSE",
    "annee": "1960",
    "temps_estime_en_minutes": 264.0
  },
  {
    "relations": "PARIS - POITIERS",
    "annee": "1960",
    "temps_estime_en_minutes": 166.0
  },
  {
    "relations": "PARIS - ST ETIENNE",
    "annee": "1960",
    "temps_estime_en_minutes": 296.0
  },
  {
    "relations": "PARIS - LYON",
    "annee": "1961",
    "temps_estime_en_minutes": 240.0
  },
  {
    "relations": "PARIS - NANTES",
    "annee": "1961",
    "temps_estime_en_minutes": 238.0
  },
  {
    "relations": "PARIS - STRASBOURG",
    "annee": "1962",
    "temps_estime_en_minutes": 251.0
  },
  {
    "relations": "LYON - NANTES",
    "annee": "1963",
    "temps_estime_en_minutes": 437.0
  },
  {
    "relations": "PARIS - AMIENS",
    "annee": "1963",
    "temps_estime_en_minutes": 65.0
  },
  {
    "relations": "PARIS - BOULOGNE",
    "annee": "1963",
    "temps_estime_en_minutes": 162.0
  },
  {
    "relations": "PARIS - CAEN",
    "annee": "1963",
    "temps_estime_en_minutes": 144.0
  },
  {
    "relations": "PARIS - DIJON",
    "annee": "1963",
    "temps_estime_en_minutes": 144.0
  },
  {
    "relations": "PARIS - LILLE",
    "annee": "1963",
    "temps_estime_en_minutes": 130.0
  },
  {
    "relations": "PARIS - METZ",
    "annee": "1963",
    "temps_estime_en_minutes": 177.0
  },
  {
    "relations": "PARIS - MONTPELLIER",
    "annee": "1963",
    "temps_estime_en_minutes": 441.0
  },
  {
    "relations": "PARIS - NANTES",
    "annee": "1963",
    "temps_estime_en_minutes": 239.0
  },
  {
    "relations": "LYON - BORDEAUX",
    "annee": "1964",
    "temps_estime_en_minutes": 517.0
  },
  {
    "relations": "LYON - STRASBOURG",
    "annee": "1964",
    "temps_estime_en_minutes": 342.0
  },
  {
    "relations": "PARIS - BOULOGNE",
    "annee": "1964",
    "temps_estime_en_minutes": 150.0
  },
  {
    "relations": "PARIS - DIJON",
    "annee": "1964",
    "temps_estime_en_minutes": 144.0
  },
  {
    "relations": "PARIS - LE HAVRE",
    "annee": "1964",
    "temps_estime_en_minutes": 147.0
  },
  {
    "relations": "PARIS - MONTPELLIER",
    "annee": "1964",
    "temps_estime_en_minutes": 441.0
  },
  {
    "relations": "PARIS - QUIMPER",
    "annee": "1964",
    "temps_estime_en_minutes": 476.0
  },
  {
    "relations": "PARIS - AMIENS",
    "annee": "1965",
    "temps_estime_en_minutes": 67.0
  },
  {
    "relations": "PARIS - BOULOGNE",
    "annee": "1965",
    "temps_estime_en_minutes": 150.0
  },
  {
    "relations": "PARIS - CLERMONT FERRAND",
    "annee": "1965",
    "temps_estime_en_minutes": 240.0
  },
  {
    "relations": "PARIS - GRENOBLE",
    "annee": "1965",
    "temps_estime_en_minutes": 368.0
  },
  {
    "relations": "PARIS - LE HAVRE",
    "annee": "1965",
    "temps_estime_en_minutes": 146.0
  },
  {
    "relations": "PARIS - LIMOGES",
    "annee": "1965",
    "temps_estime_en_minutes": 197.0
  },
  {
    "relations": "PARIS - NANTES",
    "annee": "1965",
    "temps_estime_en_minutes": 239.0
  },
  {
    "relations": "LYON - BORDEAUX",
    "annee": "1966",
    "temps_estime_en_minutes": 517.0
  },
  {
    "relations": "PARIS - CHERBOURG",
    "annee": "1966",
    "temps_estime_en_minutes": 231.0
  },
  {
    "relations": "PARIS - LE HAVRE",
    "annee": "1966",
    "temps_estime_en_minutes": 141.0
  },
  {
    "relations": "PARIS - LIMOGES",
    "annee": "1966",
    "temps_estime_en_minutes": 195.0
  },
  {
    "relations": "PARIS - ORLEANS",
    "annee": "1966",
    "temps_estime_en_minutes": 65.0
  },
  {
    "relations": "PARIS - POITIERS",
    "annee": "1966",
    "temps_estime_en_minutes": 166.0
  },
  {
    "relations": "PARIS - STRASBOURG",
    "annee": "1966",
    "temps_estime_en_minutes": 251.0
  },
  {
    "relations": "LYON - NANTES",
    "annee": "1967",
    "temps_estime_en_minutes": 436.0
  },
  {
    "relations": "PARIS - LIMOGES",
    "annee": "1967",
    "temps_estime_en_minutes": 172.0
  },
  {
    "relations": "PARIS - LYON",
    "annee": "1967",
    "temps_estime_en_minutes": 240.0
  },
  {
    "relations": "PARIS - ST ETIENNE",
    "annee": "1967",
    "temps_estime_en_minutes": 293.0
  },
  {
    "relations": "PARIS - BORDEAUX",
    "annee": "1968",
    "temps_estime_en_minutes": 260.0
  },
  {
    "relations": "PARIS - CHERBOURG",
    "annee": "1968",
    "temps_estime_en_minutes": 229.0
  },
  {
    "relations": "PARIS - LA ROCHELLE",
    "annee": "1968",
    "temps_estime_en_minutes": 279.0
  },
  {
    "relations": "PARIS - LILLE",
    "annee": "1968",
    "temps_estime_en_minutes": 115.0
  },
  {
    "relations": "PARIS - MARSEILLE",
    "annee": "1968",
    "temps_estime_en_minutes": 420.0
  },
  {
    "relations": "PARIS - MULHOUSE",
    "annee": "1968",
    "temps_estime_en_minutes": 280.0
  },
  {
    "relations": "PARIS - POITIERS",
    "annee": "1968",
    "temps_estime_en_minutes": 148.0
  },
  {
    "relations": "PARIS - QUIMPER",
    "annee": "1968",
    "temps_estime_en_minutes": 353.0
  },
  {
    "relations": "LYON - STRASBOURG",
    "annee": "1969",
    "temps_estime_en_minutes": 314.0
  },
  {
    "relations": "PARIS - CLERMONT FERRAND",
    "annee": "1969",
    "temps_estime_en_minutes": 240.0
  },
  {
    "relations": "PARIS - GRENOBLE",
    "annee": "1969",
    "temps_estime_en_minutes": 323.0
  },
  {
    "relations": "PARIS - MARSEILLE",
    "annee": "1969",
    "temps_estime_en_minutes": 400.0
  },
  {
    "relations": "PARIS - MONTPELLIER",
    "annee": "1969",
    "temps_estime_en_minutes": 419.0
  },
  {
    "relations": "PARIS - MULHOUSE",
    "annee": "1969",
    "temps_estime_en_minutes": 270.0
  },
  {
    "relations": "PARIS - NICE",
    "annee": "1969",
    "temps_estime_en_minutes": 546.0
  },
  {
    "relations": "PARIS - STRASBOURG",
    "annee": "1969",
    "temps_estime_en_minutes": 237.0
  },
  {
    "relations": "PARIS - MONTPELLIER",
    "annee": "1970",
    "temps_estime_en_minutes": 419.0
  },
  {
    "relations": "PARIS - MULHOUSE",
    "annee": "1970",
    "temps_estime_en_minutes": 242.0
  },
  {
    "relations": "PARIS - RENNES",
    "annee": "1970",
    "temps_estime_en_minutes": 180.0
  },
  {
    "relations": "PARIS - ST ETIENNE",
    "annee": "1970",
    "temps_estime_en_minutes": 285.0
  },
  {
    "relations": "LYON - STRASBOURG",
    "annee": "1971",
    "temps_estime_en_minutes": 314.0
  },
  {
    "relations": "PARIS - BOULOGNE",
    "annee": "1971",
    "temps_estime_en_minutes": 142.0
  },
  {
    "relations": "PARIS - BREST",
    "annee": "1971",
    "temps_estime_en_minutes": 327.0
  },
  {
    "relations": "PARIS - LE HAVRE",
    "annee": "1971",
    "temps_estime_en_minutes": 107.0
  },
  {
    "relations": "PARIS - LYON",
    "annee": "1971",
    "temps_estime_en_minutes": 223.0
  },
  {
    "relations": "PARIS - ORLEANS",
    "annee": "1971",
    "temps_estime_en_minutes": 58.0
  },
  {
    "relations": "PARIS - POITIERS",
    "annee": "1971",
    "temps_estime_en_minutes": 139.0
  },
  {
    "relations": "PARIS - QUIMPER",
    "annee": "1971",
    "temps_estime_en_minutes": 336.0
  },
  {
    "relations": "PARIS - STRASBOURG",
    "annee": "1971",
    "temps_estime_en_minutes": 228.0
  },
  {
    "relations": "PARIS - TOULOUSE",
    "annee": "1971",
    "temps_estime_en_minutes": 356.0
  },
  {
    "relations": "LYON - NANTES",
    "annee": "1972",
    "temps_estime_en_minutes": 409.0
  },
  {
    "relations": "PARIS - BORDEAUX",
    "annee": "1972",
    "temps_estime_en_minutes": 240.0
  },
  {
    "relations": "PARIS - BOULOGNE",
    "annee": "1972",
    "temps_estime_en_minutes": 142.0
  },
  {
    "relations": "PARIS - LA ROCHELLE",
    "annee": "1972",
    "temps_estime_en_minutes": 249.0
  },
  {
    "relations": "PARIS - LYON",
    "annee": "1972",
    "temps_estime_en_minutes": 224.0
  },
  {
    "relations": "PARIS - MONTPELLIER",
    "annee": "1972",
    "temps_estime_en_minutes": 412.0
  },
  {
    "relations": "PARIS - POITIERS",
    "annee": "1972",
    "temps_estime_en_minutes": 139.0
  },
  {
    "relations": "PARIS - STRASBOURG",
    "annee": "1972",
    "temps_estime_en_minutes": 228.0
  },
  {
    "relations": "BORDEAUX - MARSEILLE",
    "annee": "1973",
    "temps_estime_en_minutes": 379.0
  },
  {
    "relations": "LYON - BORDEAUX",
    "annee": "1973",
    "temps_estime_en_minutes": 471.0
  },
  {
    "relations": "PARIS - AMIENS",
    "annee": "1973",
    "temps_estime_en_minutes": 59.0
  },
  {
    "relations": "PARIS - BORDEAUX",
    "annee": "1973",
    "temps_estime_en_minutes": 240.0
  },
  {
    "relations": "PARIS - CAEN",
    "annee": "1973",
    "temps_estime_en_minutes": 108.0
  },
  {
    "relations": "PARIS - LIMOGES",
    "annee": "1973",
    "temps_estime_en_minutes": 170.0
  },
  {
    "relations": "PARIS - LYON",
    "annee": "1973",
    "temps_estime_en_minutes": 226.0
  },
  {
    "relations": "PARIS - MARSEILLE",
    "annee": "1973",
    "temps_estime_en_minutes": 394.0
  },
  {
    "relations": "PARIS - METZ",
    "annee": "1973",
    "temps_estime_en_minutes": 160.0
  },
  {
    "relations": "PARIS - MONTPELLIER",
    "annee": "1973",
    "temps_estime_en_minutes": 415.0
  },
  {
    "relations": "PARIS - MULHOUSE",
    "annee": "1973",
    "temps_estime_en_minutes": 252.0
  },
  {
    "relations": "PARIS - ORLEANS",
    "annee": "1973",
    "temps_estime_en_minutes": 58.0
  },
  {
    "relations": "PARIS - ROUEN",
    "annee": "1973",
    "temps_estime_en_minutes": 63.0
  },
  {
    "relations": "PARIS - STRASBOURG",
    "annee": "1973",
    "temps_estime_en_minutes": 227.0
  },
  {
    "relations": "PARIS - CLERMONT FERRAND",
    "annee": "1974",
    "temps_estime_en_minutes": 238.0
  },
  {
    "relations": "PARIS - GRENOBLE",
    "annee": "1974",
    "temps_estime_en_minutes": 316.0
  },
  {
    "relations": "PARIS - LIMOGES",
    "annee": "1974",
    "temps_estime_en_minutes": 170.0
  },
  {
    "relations": "PARIS - MONTPELLIER",
    "annee": "1974",
    "temps_estime_en_minutes": 415.0
  },
  {
    "relations": "PARIS - MULHOUSE",
    "annee": "1974",
    "temps_estime_en_minutes": 248.0
  },
  {
    "relations": "PARIS - ORLEANS",
    "annee": "1974",
    "temps_estime_en_minutes": 59.0
  },
  {
    "relations": "LYON - NANTES",
    "annee": "1975",
    "temps_estime_en_minutes": 367.0
  },
  {
    "relations": "PARIS - LYON",
    "annee": "1975",
    "temps_estime_en_minutes": 224.0
  },
  {
    "relations": "PARIS - MONTPELLIER",
    "annee": "1975",
    "temps_estime_en_minutes": 415.0
  },
  {
    "relations": "PARIS - NANTES",
    "annee": "1975",
    "temps_estime_en_minutes": 185.0
  },
  {
    "relations": "PARIS - QUIMPER",
    "annee": "1975",
    "temps_estime_en_minutes": 328.0
  },
  {
    "relations": "LYON - NANTES",
    "annee": "1976",
    "temps_estime_en_minutes": 369.0
  },
  {
    "relations": "PARIS - DIJON",
    "annee": "1976",
    "temps_estime_en_minutes": 137.0
  },
  {
    "relations": "PARIS - ST ETIENNE",
    "annee": "1976",
    "temps_estime_en_minutes": 281.0
  },
  {
    "relations": "PARIS - BORDEAUX",
    "annee": "1977",
    "temps_estime_en_minutes": 230.0
  },
  {
    "relations": "PARIS - CAEN",
    "annee": "1977",
    "temps_estime_en_minutes": 109.0
  },
  {
    "relations": "PARIS - LILLE",
    "annee": "1977",
    "temps_estime_en_minutes": 119.0
  },
  {
    "relations": "PARIS - NARBONNE",
    "annee": "1977",
    "temps_estime_en_minutes": 449.0
  },
  {
    "relations": "PARIS - NICE",
    "annee": "1977",
    "temps_estime_en_minutes": 541.0
  },
  {
    "relations": "PARIS - POITIERS",
    "annee": "1977",
    "temps_estime_en_minutes": 130.0
  },
  {
    "relations": "PARIS - REIMS",
    "annee": "1977",
    "temps_estime_en_minutes": 87.0
  },
  {
    "relations": "PARIS - AMIENS",
    "annee": "1978",
    "temps_estime_en_minutes": 60.0
  },
  {
    "relations": "PARIS - CHERBOURG",
    "annee": "1978",
    "temps_estime_en_minutes": 186.0
  },
  {
    "relations": "PARIS - MULHOUSE",
    "annee": "1978",
    "temps_estime_en_minutes": 261.0
  },
  {
    "relations": "PARIS - NANCY",
    "annee": "1978",
    "temps_estime_en_minutes": 157.0
  },
  {
    "relations": "PARIS - ORLEANS",
    "annee": "1978",
    "temps_estime_en_minutes": 62.0
  },
  {
    "relations": "PARIS - POITIERS",
    "annee": "1978",
    "temps_estime_en_minutes": 130.0
  },
  {
    "relations": "PARIS - ROUEN",
    "annee": "1978",
    "temps_estime_en_minutes": 67.0
  },
  {
    "relations": "PARIS - ST ETIENNE",
    "annee": "1978",
    "temps_estime_en_minutes": 282.0
  },
  {
    "relations": "PARIS - TOULOUSE",
    "annee": "1978",
    "temps_estime_en_minutes": 362.0
  },
  {
    "relations": "PARIS - BORDEAUX",
    "annee": "1979",
    "temps_estime_en_minutes": 230.0
  },
  {
    "relations": "PARIS - BREST",
    "annee": "1979",
    "temps_estime_en_minutes": 328.0
  },
  {
    "relations": "PARIS - CHERBOURG",
    "annee": "1979",
    "temps_estime_en_minutes": 184.0
  },
  {
    "relations": "PARIS - LILLE",
    "annee": "1979",
    "temps_estime_en_minutes": 112.0
  },
  {
    "relations": "PARIS - MARSEILLE",
    "annee": "1979",
    "temps_estime_en_minutes": 398.0
  },
  {
    "relations": "PARIS - NANTES",
    "annee": "1979",
    "temps_estime_en_minutes": 187.0
  },
  {
    "relations": "PARIS - ST ETIENNE",
    "annee": "1979",
    "temps_estime_en_minutes": 283.0
  },
  {
    "relations": "PARIS - TOULOUSE",
    "annee": "1979",
    "temps_estime_en_minutes": 362.0
  },
  {
    "relations": "LYON - NANTES",
    "annee": "1980",
    "temps_estime_en_minutes": 379.0
  },
  {
    "relations": "PARIS - BOULOGNE",
    "annee": "1980",
    "temps_estime_en_minutes": 133.0
  },
  {
    "relations": "PARIS - LA ROCHELLE",
    "annee": "1980",
    "temps_estime_en_minutes": 230.0
  },
  {
    "relations": "PARIS - LYON",
    "annee": "1980",
    "temps_estime_en_minutes": 226.0
  },
  {
    "relations": "PARIS - METZ",
    "annee": "1980",
    "temps_estime_en_minutes": 163.0
  },
  {
    "relations": "PARIS - ORLEANS",
    "annee": "1980",
    "temps_estime_en_minutes": 60.0
  },
  {
    "relations": "PARIS - TOULOUSE",
    "annee": "1980",
    "temps_estime_en_minutes": 362.0
  },
  {
    "relations": "PARIS - AMIENS",
    "annee": "1981",
    "temps_estime_en_minutes": 62.0
  },
  {
    "relations": "PARIS - LA ROCHELLE",
    "annee": "1981",
    "temps_estime_en_minutes": 239.0
  },
  {
    "relations": "PARIS - NANCY",
    "annee": "1981",
    "temps_estime_en_minutes": 162.0
  },
  {
    "relations": "PARIS - NARBONNE",
    "annee": "1981",
    "temps_estime_en_minutes": 454.0
  },
  {
    "relations": "PARIS - POITIERS",
    "annee": "1981",
    "temps_estime_en_minutes": 131.0
  },
  {
    "relations": "PARIS - ROUEN",
    "annee": "1981",
    "temps_estime_en_minutes": 68.0
  },
  {
    "relations": "PARIS - TOULOUSE",
    "annee": "1981",
    "temps_estime_en_minutes": 362.0
  },
  {
    "relations": "BORDEAUX - MARSEILLE",
    "annee": "1982",
    "temps_estime_en_minutes": 372.0
  },
  {
    "relations": "PARIS - BAYONNE",
    "annee": "1982",
    "temps_estime_en_minutes": 353.0
  },
  {
    "relations": "PARIS - BOULOGNE",
    "annee": "1982",
    "temps_estime_en_minutes": 138.0
  },
  {
    "relations": "PARIS - CHERBOURG",
    "annee": "1982",
    "temps_estime_en_minutes": 183.0
  },
  {
    "relations": "PARIS - CLERMONT FERRAND",
    "annee": "1982",
    "temps_estime_en_minutes": 225.0
  },
  {
    "relations": "PARIS - MONTPELLIER",
    "annee": "1982",
    "temps_estime_en_minutes": 334.0
  },
  {
    "relations": "PARIS - NANCY",
    "annee": "1982",
    "temps_estime_en_minutes": 152.0
  },
  {
    "relations": "PARIS - NICE",
    "annee": "1982",
    "temps_estime_en_minutes": 489.0
  },
  {
    "relations": "LYON - NANTES",
    "annee": "1983",
    "temps_estime_en_minutes": 390.0
  },
  {
    "relations": "PARIS - BORDEAUX",
    "annee": "1983",
    "temps_estime_en_minutes": 243.0
  },
  {
    "relations": "PARIS - NICE",
    "annee": "2017",
    "temps_estime_en_minutes": 333.0
  },
  {
    "relations": "PARIS - ORLEANS",
    "annee": "2017",
    "temps_estime_en_minutes": 65.0
  },
  {
    "relations": "PARIS - STRASBOURG",
    "annee": "2017",
    "temps_estime_en_minutes": 106.0
  },
  {
    "relations": "PARIS - TOURS",
    "annee": "2017",
    "temps_estime_en_minutes": 70.0
  },
  {
    "relations": "BORDEAUX - LILLE",
    "annee": "2018",
    "temps_estime_en_minutes": 252.0
  },
  {
    "relations": "LYON - LILLE",
    "annee": "2018",
    "temps_estime_en_minutes": 177.0
  },
  {
    "relations": "LYON - NANTES",
    "annee": "2018",
    "temps_estime_en_minutes": 264.0
  },
  {
    "relations": "LYON - ROUEN",
    "annee": "2018",
    "temps_estime_en_minutes": 224.0
  },
  {
    "relations": "PARIS - BAYONNE",
    "annee": "2018",
    "temps_estime_en_minutes": 234.0
  },
  {
    "relations": "PARIS - CAEN",
    "annee": "2018",
    "temps_estime_en_minutes": 110.0
  },
  {
    "relations": "PARIS - CHERBOURG",
    "annee": "2018",
    "temps_estime_en_minutes": 187.0
  },
  {
    "relations": "PARIS - LE MANS",
    "annee": "2018",
    "temps_estime_en_minutes": 54.0
  },
  {
    "relations": "PARIS - LIMOGES",
    "annee": "2018",
    "temps_estime_en_minutes": 191.0
  },
  {
    "relations": "PARIS - METZ",
    "annee": "2018",
    "temps_estime_en_minutes": 83.0
  },
  {
    "relations": "PARIS - TOULOUSE",
    "annee": "2018",
    "temps_estime_en_minutes": 247.0
  },
  {
    "relations": "BORDEAUX - LILLE",
    "annee": "2019",
    "temps_estime_en_minutes": 272.0
  },
  {
    "relations": "PARIS - BAYONNE",
    "annee": "2019",
    "temps_estime_en_minutes": 234.0
  },
  {
    "relations": "PARIS - BORDEAUX",
    "annee": "2019",
    "temps_estime_en_minutes": 120.0
  },
  {
    "relations": "PARIS - CHERBOURG",
    "annee": "2019",
    "temps_estime_en_minutes": 187.0
  },
  {
    "relations": "PARIS - LILLE",
    "annee": "2019",
    "temps_estime_en_minutes": 57.0
  },
  {
    "relations": "PARIS - QUIMPER",
    "annee": "2019",
    "temps_estime_en_minutes": 196.0
  },
  {
    "relations": "PARIS - STRASBOURG",
    "annee": "2019",
    "temps_estime_en_minutes": 103.0
  }
]